CanDI/__init__.py
CanDI/__version__.py
CanDI/candi/__init__.py
CanDI/candi/candi.py
CanDI/candi/data.py
CanDI/candi/grabber.py
CanDI/pipelines/__init__.py
CanDI/pipelines/diffexp.py
CanDI/pipelines/coessentiality/__init__.py
CanDI/setup/__init__.py
CanDI/setup/dataverse.py
CanDI/setup/install.py
CanDI/setup/manager.py
CanDI/setup/reset_config.py
CanDI/setup/uninstall.py
CanDI/setup/data/config.draft.ini
CanDI/setup/data/genes/gene_info.csv
CanDI/setup/data/locations/merged_locations.csv
CanDI/structures/__init__.py
CanDI/structures/entity.py
CanDI/structures/handlers.py
PyCanDI-0.2.5.dist-info/LICENSE
PyCanDI-0.2.5.dist-info/METADATA
PyCanDI-0.2.5.dist-info/WHEEL
PyCanDI-0.2.5.dist-info/entry_points.txt
PyCanDI-0.2.5.dist-info/top_level.txt
PyCanDI-0.2.5.dist-info/RECORD
