Metadata-Version: 2.1
Name: PyCanDI
Version: 0.2.5
Summary: A cancer data integration package
Home-page: https://github.com/GilbertLabUCSF/CanDI
Classifier: Intended Audience :: Science/Research
Classifier: License :: OSI Approved :: MIT License
Classifier: Programming Language :: Python :: 3
Requires-Python: >=3.11,<4.0
License-File: LICENSE
Requires-Dist: pandas
Requires-Dist: configparser
Requires-Dist: requests
Requires-Dist: tqdm
